assetic_qgis/__init__.py
assetic_qgis/__version__.py
assetic_qgis/initialise.py
assetic_qgis/qgis_config.py
assetic_qgis/tools/__init__.py
assetic_qgis/tools/qgis_layertools.py
assetic_qgis/tools/qgis_messager.py
assetic_qgis-2.1.0.4.dist-info/LICENSE.txt
assetic_qgis-2.1.0.4.dist-info/METADATA
assetic_qgis-2.1.0.4.dist-info/WHEEL
assetic_qgis-2.1.0.4.dist-info/top_level.txt
assetic_qgis-2.1.0.4.dist-info/RECORD
