Metadata-Version: 2.1
Name: assetic_qgis
Version: 2.1.0.4
Summary: Assetic QGis Integration API
Home-page: http://www.assetic.com
Author-email: developer@assetic.com
Keywords: Assetic QGis Integration APIs
License-File: LICENSE.txt
Requires-Dist: assetic >=2023.16.1.3
Requires-Dist: PyQt5
